{
    "users_notifications": [
        {
            "id": "69bbd466480ef",
            "notiId": "69bbcc44b5377",
            "userId": "65e10aa11a001" 
        },
        {
            "id": "69bbd478a6a16",
            "notiId": "69bbcc44b5377",
            "userId": "65e10aa11a002"
        },
        {
            "id": "69bbd4c913172",
            "notiId": "69bbce7c49da1",
            "userId": "65e10aa11a003"
        },
        {
            "id": "69bbd4e1ccf8b",
            "notiId": "69bbd002ab5b8",
            "userId": "65e10aa11a002"
        },
        {
            "id": "69bbd4f174546",
            "notiId": "69bbd0f08ba4a",
            "userId": "65e10aa11a001"
        },
        {
            "id": "69bbd502ef38f",
            "notiId": "69bbd0f08ba4a",
            "userId": "65e10aa11a002"
        }
    ]
}